django_readonly_field/__init__.py
django_readonly_field/apps.py
django_readonly_field/compiler.py
django_readonly_field-1.3.0.dist-info/AUTHORS.rst
django_readonly_field-1.3.0.dist-info/LICENSE
django_readonly_field-1.3.0.dist-info/METADATA
django_readonly_field-1.3.0.dist-info/WHEEL
django_readonly_field-1.3.0.dist-info/RECORD
