Metadata-Version: 2.1
Name: django-readonly-field
Version: 1.3.0
Summary: Make Django model fields readonly
Home-page: https://github.com/botify-labs/django-readonly-field
License: MIT
Keywords: django,posgresql,read-only
Author: Joachim Jablon
Author-email: ewjoachim@gmail.com
Maintainer: Sofien Ben Ayed
Maintainer-email: sofien@botify.com
Requires-Python: >=3.8,<4.0
Classifier: Development Status :: 5 - Production/Stable
Classifier: Framework :: Django
Classifier: Framework :: Django :: 4.2
Classifier: Framework :: Django :: 5.0
Classifier: Framework :: Django :: 5.1
Classifier: Intended Audience :: Developers
Classifier: License :: OSI Approved :: MIT License
Classifier: Programming Language :: Python :: 3
Classifier: Programming Language :: Python :: 3.8
Classifier: Programming Language :: Python :: 3.9
Classifier: Programming Language :: Python :: 3.10
Classifier: Programming Language :: Python :: 3.11
Classifier: Programming Language :: Python :: 3.12
Requires-Dist: django
Project-URL: Documentation, https://django-readonly-field.readthedocs.io/en/latest/
Project-URL: Repository, https://github.com/botify-labs/django-readonly-field
